zoomegastash/__init__.py
zoomegastash/__main__.py
zoomegastash/_version.py
zoomegastash/src/zms_announce.py
zoomegastash/src/zms_consts.py
zoomegastash/src/zms_profiles.py
zoomegastash/src/zms_rate.py
zoomegastash/src/zms_types.py
zoomegastash-0.1.4.dist-info/LICENSE
zoomegastash-0.1.4.dist-info/METADATA
zoomegastash-0.1.4.dist-info/WHEEL
zoomegastash-0.1.4.dist-info/RECORD
